pydeno_core-0.1.0.dist-info/METADATA
pydeno_core-0.1.0.dist-info/WHEEL
deno_core/__init__.py
deno_core/deno_core.cpython-39-darwin.so
pydeno_core-0.1.0.dist-info/RECORD
